gpu_scheduler/__init__.py
gpu_scheduler/gpu_scheduler.py
gpu_scheduler-0.1.1.dist-info/METADATA
gpu_scheduler-0.1.1.dist-info/WHEEL
gpu_scheduler-0.1.1.dist-info/RECORD
