Metadata-Version: 2.4
Name: gpu-scheduler
Version: 0.1.1
Summary: A simple tool to schedule gpu resources.
Project-URL: Homepage, https://github.com/dipta007/gpu-scheduler
Project-URL: Bug Tracker, https://github.com/dipta007/gpu-scheduler/issues
Author-email: Shubhashis Roy Dipta <iamdipta@gmail.com>
Requires-Python: >=3.10
